[
    {
        "id": 1,
        "title": "New ES6 upgrade available",
        "feed": "What does our page want? It wants to provide an id and get a Happening  "
    },
    {
        "id": 7,
        "title": "New ES6 upgrade available",
        "feed": "What does our page want? It wants to provide an id and get a Happening  "
    },
    {
        "id": 2,
        "title": "New ES4 upgrade available",
        "feed": "What does our page want? It wants to provide an id and get a Happening  "
    },
    {
        "id": 3,
        "title": "New ES3 upgrade available",
        "feed": "What does our page want? It wants to provide an id and get a Happening  "
    },
    {
        "id": 4,
        "title": "New ES2 upgrade available",
        "feed": "It wants to provide an id and get a Happening  "
    },
    {
        "id": 5,
        "title": "New ES1 upgrade available",
        "feed": "What does our page want? It wants to provide an id and get a Happening  "
    }
  
]